darkdetect/__init__.py
darkdetect/__main__.py
darkdetect/_base_listener.py
darkdetect/_dummy.py
darkdetect/_linux_detect.py
darkdetect/_mac_detect.py
darkdetect/_windows_detect.py
darkdetect/py.typed
darkdetect_angr-0.9.1.dist-info/LICENSE
darkdetect_angr-0.9.1.dist-info/METADATA
darkdetect_angr-0.9.1.dist-info/WHEEL
darkdetect_angr-0.9.1.dist-info/top_level.txt
darkdetect_angr-0.9.1.dist-info/RECORD
