Metadata-Version: 2.1
Name: darkdetect-angr
Version: 0.9.1
Summary: Detect OS Dark Mode from Python
Author-email: Zachary Wimer <zwimer@gmail.com>
License: BSD-3-Clause
Project-URL: homepage, http://github.com/zwimer/darkdetect
Project-URL: download, http://github.com/zwimer/darkdetect/releases
Classifier: License :: OSI Approved :: BSD License
Classifier: Operating System :: MacOS :: MacOS X
Classifier: Operating System :: Microsoft :: Windows :: Windows 10
Classifier: Operating System :: POSIX :: Linux
Classifier: Programming Language :: Python :: 3
Classifier: Programming Language :: Python :: 3.6
Classifier: Programming Language :: Python :: 3.7
Classifier: Programming Language :: Python :: 3.8
Classifier: Programming Language :: Python :: 3.9
Classifier: Programming Language :: Python :: 3.10
Requires-Python: >=3.6
License-File: LICENSE
Provides-Extra: macos-listener
Requires-Dist: pyobjc-framework-Cocoa ; (platform_system == "Darwin") and extra == 'macos-listener'
